[
null,
{"id":1,"battlerName":"","characterIndex":3,"characterName":"New_Characters 48x48 200","classId":1,"equips":[0,0,0,0,0],"faceIndex":0,"faceName":"Actor2","traits":[],"initialLevel":1,"maxLevel":99,"name":"Magnolia","nickname":"","note":"<battle command: attack />","profile":""},
{"id":2,"battlerName":"","characterIndex":2,"characterName":"New_Characters 48x48 200","classId":2,"equips":[0,0,0,0,0],"faceIndex":0,"faceName":"Actor1","traits":[],"initialLevel":1,"maxLevel":99,"name":"Mint","nickname":"","note":"","profile":""},
{"id":3,"battlerName":"","characterIndex":0,"characterName":"","classId":1,"equips":[0,0,0,0,0],"faceIndex":0,"faceName":"","traits":[],"initialLevel":1,"maxLevel":99,"name":"","nickname":"","note":"","profile":""},
{"id":4,"battlerName":"","characterIndex":0,"characterName":"","classId":1,"equips":[0,0,0,0,0],"faceIndex":0,"faceName":"","traits":[],"initialLevel":1,"maxLevel":99,"name":"","nickname":"","note":"","profile":""}
]